{"data":{"cases.diaries.787.2019-09-01_to_2019-09-07":[{"diary_no":322742019,"reg_no_display":"","pet_name":"UNION OF INDIA","res_name":"BRAHAM PRAKASH","pno":3,"rno":1,"next date":"","diary date":"2019-09-04 15:41:02"},{"diary_no":320122019,"reg_no_display":"MA 521-523\/2020 in Crl.A. No. 376-378\/2004","pet_name":"STATE (GOVT. OF N.C.T. OF DELHI)","res_name":"SYED ABDUL REHMAN GILLANI","pno":1,"rno":1,"next date":"","diary date":"2019-09-03 11:13:30"},{"diary_no":322752019,"reg_no_display":"","pet_name":"UNION OF INDIA","res_name":"SANJAY","pno":3,"rno":4,"next date":"","diary date":"2019-09-04 15:45:44"},{"diary_no":324992019,"reg_no_display":"SLP(C) No. 24268-24269\/2019","pet_name":"THE DIRECTOR OF CENSUS OPERATIONS","res_name":"C D ANABANDAN","pno":2,"rno":1,"next date":"","diary date":"2019-09-06 11:30:53"},{"diary_no":325002019,"reg_no_display":"","pet_name":"THE STATE (NCT) OF DELHI","res_name":"R.K. BAHRI","pno":1,"rno":7,"next date":"","diary date":"2019-09-06 11:33:02"},{"diary_no":325252019,"reg_no_display":"SLP(C) No. 23760\/2019","pet_name":"UNION OF INDIA","res_name":"SUNITA ALURKAR NEE SUNITA KULKARNI","pno":3,"rno":8,"next date":"","diary date":"2019-09-06 12:26:40"},{"diary_no":326232019,"reg_no_display":"SLP(C) No. 23785\/2019","pet_name":"UNION OF INDIA","res_name":"RAMESH CHANDRA SINGH","pno":3,"rno":1,"next date":"","diary date":"2019-09-06 15:37:52"}],"cases.defects_notified.787.2019-09-01_to_2019-09-07":[{"diary_no":322742019,"reg_no_display":"","pet_name":"UNION OF INDIA","res_name":"BRAHAM PRAKASH","pno":3,"rno":1,"next_date":"","diary_date":"2019-09-04 15:41:02","defects_notified":"2019-09-05"},{"diary_no":281872019,"reg_no_display":"SLP(C) No. 22079\/2019","pet_name":"UNION OF INDIA","res_name":"SHAM SINGH","pno":2,"rno":1,"next_date":"","diary_date":"2019-08-07 14:15:13","defects_notified":"2019-09-02"},{"diary_no":313862019,"reg_no_display":"SLP(C) No. 23784\/2019","pet_name":"DIRECTOR GENERAL OF POLICE CENTRAL RESERVE POLICE FORCE","res_name":"YOGENDRA","pno":6,"rno":3,"next_date":"","diary_date":"2019-08-29 12:44:47","defects_notified":"2019-09-02"},{"diary_no":322752019,"reg_no_display":"","pet_name":"UNION OF INDIA","res_name":"SANJAY","pno":3,"rno":4,"next_date":"","diary_date":"2019-09-04 15:45:44","defects_notified":"2019-09-05"},{"diary_no":325252019,"reg_no_display":"SLP(C) No. 23760\/2019","pet_name":"UNION OF INDIA","res_name":"SUNITA ALURKAR NEE SUNITA KULKARNI","pno":3,"rno":8,"next_date":"","diary_date":"2019-09-06 12:26:40","defects_notified":"2019-09-06"},{"diary_no":322002019,"reg_no_display":"SLP(Crl) No. 8111\/2019","pet_name":"ADVANTAGE INDIA","res_name":"UNION OF INDIA","pno":2,"rno":3,"next_date":"","diary_date":"2019-09-04 12:40:41","defects_notified":"2019-09-04"},{"diary_no":323162019,"reg_no_display":"SLP(Crl) No. 8174\/2019","pet_name":"M\/S ADVANTAGE INDIA","res_name":"UNION OF INDIA","pno":5,"rno":5,"next_date":"","diary_date":"2019-09-04 18:02:43","defects_notified":"2019-09-05"},{"diary_no":325132019,"reg_no_display":"W.P.(C) No. 1166\/2019","pet_name":"ENAKSHI GANGULY","res_name":"UNION OF INDIA","pno":2,"rno":4,"next_date":"","diary_date":"2019-09-06 11:52:52","defects_notified":"2019-09-06"},{"diary_no":320632019,"reg_no_display":"SLP(C) No. 21477\/2019","pet_name":"PARAMJIT SINGH NAGI","res_name":"UNION OF INDIA","pno":1,"rno":4,"next_date":"2020-04-09","diary_date":"2019-09-03 14:36:40","defects_notified":"2019-09-04"},{"diary_no":317252019,"reg_no_display":"SLP(C) No. 22112\/2019","pet_name":"KANCHAN SAXENA","res_name":"UNION OF INDIA","pno":1,"rno":4,"next_date":"","diary_date":"2019-08-30 18:41:46","defects_notified":"2019-09-02"},{"diary_no":318382019,"reg_no_display":"SLP(C) No. 24190-24191\/2019","pet_name":"SUNIL SHARMA","res_name":"CRPF THROUGH THE DIRECTOR GENERAL","pno":1,"rno":4,"next_date":"","diary_date":"2019-09-02 11:38:25","defects_notified":"2019-09-03"}],"cases.registered.787.2019-09-01_to_2019-09-07":[{"diary_no":252282019,"reg_no_display":"SLP(C) No. 21211-21212\/2019","pet_name":"UNION OF INDIA","res_name":"TANAKA RAM","pno":3,"rno":52,"next date":"","diary date":"2019-07-18 16:21:58","registration date":"2019-09-02"},{"diary_no":266032019,"reg_no_display":"SLP(C) No. 21309-21310\/2019","pet_name":"UNION OF INDIA","res_name":"PRAMOD KUMAR SHUKLA","pno":4,"rno":13,"next date":"","diary date":"2019-07-29 11:25:21","registration date":"2019-09-02"},{"diary_no":274622019,"reg_no_display":"SLP(C) No. 21215\/2019","pet_name":"UNION OF INDIA","res_name":"041664366 CT\/GD BICHITRA SARMAH","pno":6,"rno":1,"next date":"","diary date":"2019-08-02 12:36:19","registration date":"2019-09-02"},{"diary_no":81042017,"reg_no_display":"C.A. No. 6990-6991\/2019","pet_name":"EX-CONSTABLE KRISHAN KUMAR","res_name":"UNION OF INDIA ","pno":1,"rno":3,"next date":"","diary date":"2017-03-10 16:30:32","registration date":"2019-09-03"},{"diary_no":322002019,"reg_no_display":"SLP(Crl) No. 8111\/2019","pet_name":"ADVANTAGE INDIA","res_name":"UNION OF INDIA","pno":2,"rno":3,"next date":"","diary date":"2019-09-04 12:40:41","registration date":"2019-09-05"},{"diary_no":323162019,"reg_no_display":"SLP(Crl) No. 8174\/2019","pet_name":"M\/S ADVANTAGE INDIA","res_name":"UNION OF INDIA","pno":5,"rno":5,"next date":"","diary date":"2019-09-04 18:02:43","registration date":"2019-09-06"},{"diary_no":320632019,"reg_no_display":"SLP(C) No. 21477\/2019","pet_name":"PARAMJIT SINGH NAGI","res_name":"UNION OF INDIA","pno":1,"rno":4,"next date":"2020-04-09","diary date":"2019-09-03 14:36:40","registration date":"2019-09-04"},{"diary_no":222982019,"reg_no_display":"SLP(Crl) No. 8138\/2019","pet_name":"JAI PARKASH","res_name":"STATE OF NCT OF DELHI","pno":1,"rno":1,"next date":"","diary date":"2019-06-29 10:49:40","registration date":"2019-09-05"},{"diary_no":221492019,"reg_no_display":"Crl.A. No. 1337\/2019","pet_name":"NARESH KUMAR","res_name":"STATE OF NCT OF DELHI","pno":1,"rno":2,"next date":"","diary date":"2019-06-28 11:24:58","registration date":"2019-09-04"}],"cases.refiled.787.2019-09-01_to_2019-09-07":[{"diary_no":null,"reg_no_display":null,"pet_name":null,"res_name":null,"pno":null,"rno":null,"next_date":"","refiled_date":null},{"diary_no":281872019,"reg_no_display":"SLP(C) No. 22079\/2019","pet_name":"UNION OF INDIA","res_name":"SHAM SINGH","pno":2,"rno":1,"next_date":"","refiled_date":"2019-09-07 11:38:00"},{"diary_no":211112019,"reg_no_display":"SLP(C) No. 24768\/2019","pet_name":"MINISTRY OF HOME AFFAIRS","res_name":"JITENDRA MISHRA","pno":2,"rno":3,"next_date":"","refiled_date":"2019-09-07 11:38:00"}],"cases.misc_dak.787.2019-09-01_to_2019-09-07":[{"diary_no":639981985,"reg_no_display":"W.P.(C) No. 13029\/1985","pet_name":"M.C. MEHTA","res_name":"UNION OF INDIA","pno":1,"rno":59,"next_date":"2020-04-07","doc_number":"135114\/2019","doc_filing_date":"2019-09-03 14:29:33","doc_title":"MISC. DOCUMENT\/OTHER-DEFECTIVE PAGES AS PER OFFICE REPORT WITH LETTER"},{"diary_no":639981985,"reg_no_display":"W.P.(C) No. 13029\/1985","pet_name":"M.C. MEHTA","res_name":"UNION OF INDIA","pno":1,"rno":59,"next_date":"2020-04-07","doc_number":"135232\/2019","doc_filing_date":"2019-09-03 15:02:26","doc_title":"AFFIDAVIT-PER BY CM"},{"diary_no":639981985,"reg_no_display":"W.P.(C) No. 13029\/1985","pet_name":"M.C. MEHTA","res_name":"UNION OF INDIA","pno":1,"rno":59,"next_date":"2020-04-07","doc_number":"136866\/2019","doc_filing_date":"2019-09-05 14:44:15","doc_title":"AFFIDAVIT-AS PER CM CT NO. 4.."},{"diary_no":639981985,"reg_no_display":"W.P.(C) No. 13029\/1985","pet_name":"M.C. MEHTA","res_name":"UNION OF INDIA","pno":1,"rno":59,"next_date":"2020-04-07","doc_number":"137444\/2019","doc_filing_date":"2019-09-06 12:33:58","doc_title":"VAKALATNAMA AND MEMO OF APPEARANCE-"},{"diary_no":639981985,"reg_no_display":"W.P.(C) No. 13029\/1985","pet_name":"M.C. MEHTA","res_name":"UNION OF INDIA","pno":1,"rno":59,"next_date":"2020-04-07","doc_number":"137920\/2019","doc_filing_date":"2019-09-06 15:19:05","doc_title":"VAKALATNAMA AND MEMO OF APPEARANCE-ALONG WITH BOARD RESOLUTION"},{"diary_no":65322016,"reg_no_display":"W.P.(C) No. 193\/2016","pet_name":"DR.ASHWANI KUMAR","res_name":"UNION OF INDIA AND ORS. MINISTRY OF SOCIAL JUSTICE AND EMPOWERMENT SECRETARY","pno":1,"rno":3,"next_date":"2020-04-14","doc_number":"135827\/2019","doc_filing_date":"2019-09-04 12:53:44","doc_title":"VAKALATNAMA AND MEMO OF APPEARANCE-"},{"diary_no":70062017,"reg_no_display":"SLP(C) No. 13296-13297\/2017","pet_name":"RAJIV CAMP SAIDABAD THROUGH GENA PRASAD PRESIDENT","res_name":"GOVT. OF NCT OF DELHI AND ORS","pno":1,"rno":6,"next_date":"2020-05-11","doc_number":"135152\/2019","doc_filing_date":"2019-09-03 14:38:57","doc_title":"LETTER-"},{"diary_no":32432018,"reg_no_display":"Crl.A. No. 66\/2019","pet_name":"RAM PHAL BANSAL","res_name":"STATE THROUGH ITS SECRETARY","pno":1,"rno":5,"next_date":"","doc_number":"137930\/2019","doc_filing_date":"2019-09-06 15:20:22","doc_title":"COUNTER AFFIDAVIT-"},{"diary_no":222732018,"reg_no_display":"C.A. No. 6431\/2019","pet_name":"KRUSHNAKANT B. PARMAR","res_name":"UNION OF INDIA","pno":1,"rno":2,"next_date":"","doc_number":"137725\/2019","doc_filing_date":"2019-09-06 14:30:59","doc_title":"PROCESS FEE-"},{"diary_no":103162015,"reg_no_display":"CONMT.PET.(C) No. 425-426\/2015 In W.P.(C) No. 523\/2002","pet_name":"JUSTICE V.S. DAVE PRESIDENT, THE ASSOCIATION OF RETD. JUDGES OF SUPREME COURT AND HIGH COURTS","res_name":"KUSUMJIT SIDHU .","pno":1,"rno":3,"next_date":"2020-04-09","doc_number":"136672\/2019","doc_filing_date":"2019-09-05 12:32:58","doc_title":"AFFIDAVIT-COMPLIANCE AFFIDAVIT - AS PER ORDER"},{"diary_no":65612018,"reg_no_display":"SLP(C) No. 10230\/2018","pet_name":"RAMENA BEGUM @ RAMENA KHATUN @ RAMANA KHATUN@ RAMALA KHATUN","res_name":"UNION OF INDIA","pno":1,"rno":6,"next_date":"2020-05-11","doc_number":"135221\/2019","doc_filing_date":"2019-09-03 14:59:02","doc_title":"COUNTER AFFIDAVIT-"},{"diary_no":473532018,"reg_no_display":"SLP(Crl) No. 510\/2019","pet_name":"UNION OF INDIA","res_name":"SUBAIR","pno":1,"rno":1,"next_date":"","doc_number":"135179\/2019","doc_filing_date":"2019-09-03 14:47:21","doc_title":"AFFIDAVIT OF SERVICE-DASTI SERVICE AFF."},{"diary_no":28441998,"reg_no_display":"W.P.(C) No. 116\/1998","pet_name":"JUSTICE SUNANDA BHANDARE FOUNDATION","res_name":"U.O.I.","pno":1,"rno":5,"next_date":"2020-05-04","doc_number":"133928\/2019","doc_filing_date":"2019-09-02 11:08:15","doc_title":"MISC. DOCUMENT\/OTHER-COMPLIANCE CHART AS PER ORDER"},{"diary_no":40082019,"reg_no_display":"SLP(C) No. 3896\/2019","pet_name":"SHYAM SUNDER OBEROI","res_name":"DISTRICT AND SESSION JUDGE","pno":6,"rno":44,"next_date":"2020-04-21","doc_number":"137908\/2019","doc_filing_date":"2019-09-06 15:13:19","doc_title":"REJOINDER AFFIDAVIT-AS PER ORDER"},{"diary_no":79522019,"reg_no_display":"C.A. No. 5246\/2019","pet_name":"COMMISSIONER OF GST AND CENTRAL EXCISE CHENNAI","res_name":"MAHINDRA HOLIDAY AND RESORTS INDIA LTD","pno":1,"rno":1,"next_date":"2020-04-21","doc_number":"137794\/2019","doc_filing_date":"2019-09-06 14:44:39","doc_title":"COUNTER AFFIDAVIT-"},{"diary_no":402332017,"reg_no_display":"SLP(Crl) No. 1136\/2018","pet_name":"MOHD. MUMTAZ","res_name":"STATE (GOVT OF NCT) OF DELHI","pno":1,"rno":1,"next_date":"","doc_number":"134770\/2019","doc_filing_date":"2019-09-03 11:40:42","doc_title":"PROCESS FEE-"},{"diary_no":16362018,"reg_no_display":"W.P.(C) No. 423\/2018","pet_name":"KANISHKA PANDEY","res_name":"UNION OF INDIA THEOUGH THE CABINET SECRETARY","pno":1,"rno":8,"next_date":"","doc_number":"134027\/2019","doc_filing_date":"2019-09-02 12:04:50","doc_title":"COUNTER AFFIDAVIT-"},{"diary_no":68192019,"reg_no_display":"Crl.A. No. 1430\/2019","pet_name":"SARITA","res_name":"STATE (GOVT. OF NCT OF DELHI)","pno":3,"rno":2,"next_date":"","doc_number":"136466\/2019","doc_filing_date":"2019-09-05 10:56:58","doc_title":"COUNTER AFFIDAVIT-"},{"diary_no":144002019,"reg_no_display":"C.A. No. 8259\/2019","pet_name":"GOVT. OF NCT DELHI","res_name":"PRADEEP KUMAR","pno":3,"rno":7,"next_date":"","doc_number":"133888\/2019","doc_filing_date":"2019-09-02 10:43:05","doc_title":"REJOINDER AFFIDAVIT-AS PER COURT ORDER DT. 21.08.2019"},{"diary_no":144002019,"reg_no_display":"C.A. No. 8259\/2019","pet_name":"GOVT. OF NCT DELHI","res_name":"PRADEEP KUMAR","pno":3,"rno":7,"next_date":"","doc_number":"134318\/2019","doc_filing_date":"2019-09-02 14:48:21","doc_title":"AFFIDAVIT OF SERVICE-AS PER COURT ORDER DT. 21.08.2019"},{"diary_no":417332017,"reg_no_display":"W.P.(C) No. 3\/2018","pet_name":"ANUJA KAPUR","res_name":"UNION OF INDIA AND ORS.","pno":1,"rno":1,"next_date":"2020-04-13","doc_number":"133924\/2019","doc_filing_date":"2019-09-02 11:06:05","doc_title":"COUNTER AFFIDAVIT-"},{"diary_no":417332017,"reg_no_display":"W.P.(C) No. 3\/2018","pet_name":"ANUJA KAPUR","res_name":"UNION OF INDIA AND ORS.","pno":1,"rno":1,"next_date":"2020-04-13","doc_number":"134387\/2019","doc_filing_date":"2019-09-02 15:19:52","doc_title":"VAKALATNAMA AND MEMO OF APPEARANCE-"},{"diary_no":417332017,"reg_no_display":"W.P.(C) No. 3\/2018","pet_name":"ANUJA KAPUR","res_name":"UNION OF INDIA AND ORS.","pno":1,"rno":1,"next_date":"2020-04-13","doc_number":"134394\/2019","doc_filing_date":"2019-09-02 15:21:42","doc_title":"COUNTER AFFIDAVIT-AS PER COURT ORDER DATED 05-08-2019"},{"diary_no":417332017,"reg_no_display":"W.P.(C) No. 3\/2018","pet_name":"ANUJA KAPUR","res_name":"UNION OF INDIA AND ORS.","pno":1,"rno":1,"next_date":"2020-04-13","doc_number":"134511\/2019","doc_filing_date":"2019-09-02 16:07:05","doc_title":"COUNTER AFFIDAVIT-AS PER COURT ORDER DT. 05-08-2019"},{"diary_no":417332017,"reg_no_display":"W.P.(C) No. 3\/2018","pet_name":"ANUJA KAPUR","res_name":"UNION OF INDIA AND ORS.","pno":1,"rno":1,"next_date":"2020-04-13","doc_number":"136294\/2019","doc_filing_date":"2019-09-04 16:08:39","doc_title":"VAKALATNAMA AND MEMO OF APPEARANCE-"},{"diary_no":417332017,"reg_no_display":"W.P.(C) No. 3\/2018","pet_name":"ANUJA KAPUR","res_name":"UNION OF INDIA AND ORS.","pno":1,"rno":1,"next_date":"2020-04-13","doc_number":"136888\/2019","doc_filing_date":"2019-09-05 14:49:52","doc_title":"MEMO OF APPEARANCE-"},{"diary_no":417332017,"reg_no_display":"W.P.(C) No. 3\/2018","pet_name":"ANUJA KAPUR","res_name":"UNION OF INDIA AND ORS.","pno":1,"rno":1,"next_date":"2020-04-13","doc_number":"136892\/2019","doc_filing_date":"2019-09-05 14:50:25","doc_title":"COUNTER AFFIDAVIT-"},{"diary_no":417332017,"reg_no_display":"W.P.(C) No. 3\/2018","pet_name":"ANUJA KAPUR","res_name":"UNION OF INDIA AND ORS.","pno":1,"rno":1,"next_date":"2020-04-13","doc_number":"137772\/2019","doc_filing_date":"2019-09-06 14:40:17","doc_title":"MEMO OF APPEARANCE-"},{"diary_no":417332017,"reg_no_display":"W.P.(C) No. 3\/2018","pet_name":"ANUJA KAPUR","res_name":"UNION OF INDIA AND ORS.","pno":1,"rno":1,"next_date":"2020-04-13","doc_number":"137778\/2019","doc_filing_date":"2019-09-06 14:40:54","doc_title":"AFFIDAVIT-AS PER PERMISSION BY CM CT 13"},{"diary_no":167532019,"reg_no_display":"SLP(C) No. 14651\/2019","pet_name":"UNION OF INDIA","res_name":"DEEPAK JYOTI GHILDIYAL","pno":1,"rno":4,"next_date":"2020-04-08","doc_number":"136806\/2019","doc_filing_date":"2019-09-05 14:25:05","doc_title":"VAKALATNAMA AND MEMO OF APPEARANCE-"},{"diary_no":167532019,"reg_no_display":"SLP(C) No. 14651\/2019","pet_name":"UNION OF INDIA","res_name":"DEEPAK JYOTI GHILDIYAL","pno":1,"rno":4,"next_date":"2020-04-08","doc_number":"138031\/2019","doc_filing_date":"2019-09-06 15:53:03","doc_title":"PROOF OF SERVICE-"},{"diary_no":167532019,"reg_no_display":"SLP(C) No. 14651\/2019","pet_name":"UNION OF INDIA","res_name":"DEEPAK JYOTI GHILDIYAL","pno":1,"rno":4,"next_date":"2020-04-08","doc_number":"138068\/2019","doc_filing_date":"2019-09-06 16:07:55","doc_title":"PROOF OF SERVICE-"},{"diary_no":179102019,"reg_no_display":"","pet_name":"UNION OF INDIA","res_name":"ABHISHEK THIMMAIAH","pno":1,"rno":1,"next_date":"","doc_number":"137038\/2019","doc_filing_date":"2019-09-05 15:51:15","doc_title":"COUNTER AFFIDAVIT-STATEMENT OF OBJECTION ON BEHALF OF RESPONDENT"},{"diary_no":179102019,"reg_no_display":"","pet_name":"UNION OF INDIA","res_name":"ABHISHEK THIMMAIAH","pno":1,"rno":1,"next_date":"","doc_number":"137041\/2019","doc_filing_date":"2019-09-05 15:52:07","doc_title":"REPLY-REPLY TO I.A. FOR CONDONATION OF DELAY"},{"diary_no":183462019,"reg_no_display":"SLP(Crl) No. 5715-5724\/2019","pet_name":"STATE","res_name":"SURENDER @ DHEERAJ","pno":1,"rno":1,"next_date":"","doc_number":"136450\/2019","doc_filing_date":"2019-09-05 10:47:56","doc_title":"VAKALATNAMA AND MEMO OF APPEARANCE-"},{"diary_no":183462019,"reg_no_display":"SLP(Crl) No. 5715-5724\/2019","pet_name":"STATE","res_name":"SURENDER @ DHEERAJ","pno":1,"rno":1,"next_date":"","doc_number":"137467\/2019","doc_filing_date":"2019-09-06 12:39:00","doc_title":"PROOF OF SERVICE-"},{"diary_no":216692019,"reg_no_display":"SLP(Crl) No. 5643\/2019","pet_name":"UNION OF INDIA NATIONAL INVESTIGATION AGENCY, ERNAKULAM","res_name":"ABDUL RASIK","pno":1,"rno":1,"next_date":"","doc_number":"135314\/2019","doc_filing_date":"2019-09-03 15:33:59","doc_title":"VAKALATNAMA AND MEMO OF APPEARANCE-"},{"diary_no":216692019,"reg_no_display":"SLP(Crl) No. 5643\/2019","pet_name":"UNION OF INDIA NATIONAL INVESTIGATION AGENCY, ERNAKULAM","res_name":"ABDUL RASIK","pno":1,"rno":1,"next_date":"","doc_number":"137464\/2019","doc_filing_date":"2019-09-06 12:37:41","doc_title":"PROOF OF SERVICE-"},{"diary_no":217552019,"reg_no_display":"SLP(Crl) No. 6270\/2019","pet_name":"STATE OF  KERALA THROUGH NATIONAL INVESTIGATION AGENCY ERNAKULAM","res_name":"SHAMMI @ SHAMMAS","pno":1,"rno":1,"next_date":"","doc_number":"135317\/2019","doc_filing_date":"2019-09-03 15:35:54","doc_title":"VAKALATNAMA AND MEMO OF APPEARANCE-"},{"diary_no":217552019,"reg_no_display":"SLP(Crl) No. 6270\/2019","pet_name":"STATE OF  KERALA THROUGH NATIONAL INVESTIGATION AGENCY ERNAKULAM","res_name":"SHAMMI @ SHAMMAS","pno":1,"rno":1,"next_date":"","doc_number":"137461\/2019","doc_filing_date":"2019-09-06 12:36:59","doc_title":"PROOF OF SERVICE-"},{"diary_no":263402019,"reg_no_display":"SLP(C) No. 21111-21112\/2019","pet_name":"CENTRAL PUBLIC INFORMATION OFFICER","res_name":"M. DINESH","pno":1,"rno":1,"next_date":"","doc_number":"137106\/2019","doc_filing_date":"2019-09-05 16:15:04","doc_title":"PROCESS FEE-"},{"diary_no":317932015,"reg_no_display":"W.P.(C) No. 795\/2015","pet_name":"VISHWA DHARMAGAM YOGASHRAM, A CHARITABLE TRUST","res_name":"UNION OF INDIA AND OTHERS","pno":1,"rno":2,"next_date":"","doc_number":"134853\/2019","doc_filing_date":"2019-09-03 12:03:19","doc_title":"COUNTER AFFIDAVIT-"},{"diary_no":266032019,"reg_no_display":"SLP(C) No. 21309-21310\/2019","pet_name":"UNION OF INDIA","res_name":"PRAMOD KUMAR SHUKLA","pno":4,"rno":13,"next_date":"","doc_number":"135732\/2019","doc_filing_date":"2019-09-04 12:14:24","doc_title":"PROCESS FEE-"},{"diary_no":171472019,"reg_no_display":"Crl.A. No. 1124\/2019","pet_name":"ASHOK THAKUR","res_name":"STATE (NCT) OF DELHI","pno":1,"rno":1,"next_date":"2020-04-15","doc_number":"134347\/2019","doc_filing_date":"2019-09-02 14:59:26","doc_title":"COUNTER AFFIDAVIT-"},{"diary_no":86402008,"reg_no_display":"W.P.(C) No. 109\/2008","pet_name":"WILDLIFE FIRST","res_name":"MINISTRY OF FOREST AND ENVIRONMENT","pno":3,"rno":17,"next_date":"","doc_number":"134720\/2019","doc_filing_date":"2019-09-03 11:21:33","doc_title":"AFFIDAVIT-RESPONSE AFF. AS PER ORDER"},{"diary_no":86402008,"reg_no_display":"W.P.(C) No. 109\/2008","pet_name":"WILDLIFE FIRST","res_name":"MINISTRY OF FOREST AND ENVIRONMENT","pno":3,"rno":17,"next_date":"","doc_number":"136868\/2019","doc_filing_date":"2019-09-05 14:44:53","doc_title":"REPORT-AS PER COURT ORDER DT 06-08-2019"},{"diary_no":86402008,"reg_no_display":"W.P.(C) No. 109\/2008","pet_name":"WILDLIFE FIRST","res_name":"MINISTRY OF FOREST AND ENVIRONMENT","pno":3,"rno":17,"next_date":"","doc_number":"136909\/2019","doc_filing_date":"2019-09-05 14:55:32","doc_title":"COUNTER AFFIDAVIT-"},{"diary_no":86402008,"reg_no_display":"W.P.(C) No. 109\/2008","pet_name":"WILDLIFE FIRST","res_name":"MINISTRY OF FOREST AND ENVIRONMENT","pno":3,"rno":17,"next_date":"","doc_number":"136943\/2019","doc_filing_date":"2019-09-05 15:14:25","doc_title":"AFFIDAVIT-SHORT AFFIDAVIT (RESPONSE) - AS PER ORDER"},{"diary_no":86402008,"reg_no_display":"W.P.(C) No. 109\/2008","pet_name":"WILDLIFE FIRST","res_name":"MINISTRY OF FOREST AND ENVIRONMENT","pno":3,"rno":17,"next_date":"","doc_number":"137086\/2019","doc_filing_date":"2019-09-05 16:03:56","doc_title":"AFFIDAVIT-COMPLIANCE AFFIDAVIT AS PER COURT ORDER DT. 06-08-2019"},{"diary_no":86402008,"reg_no_display":"W.P.(C) No. 109\/2008","pet_name":"WILDLIFE FIRST","res_name":"MINISTRY OF FOREST AND ENVIRONMENT","pno":3,"rno":17,"next_date":"","doc_number":"137511\/2019","doc_filing_date":"2019-09-06 12:47:19","doc_title":"AFFIDAVIT-COMPLIANCE AFF. AS PER ORDER"},{"diary_no":86402008,"reg_no_display":"W.P.(C) No. 109\/2008","pet_name":"WILDLIFE FIRST","res_name":"MINISTRY OF FOREST AND ENVIRONMENT","pno":3,"rno":17,"next_date":"","doc_number":"137958\/2019","doc_filing_date":"2019-09-06 15:26:56","doc_title":"AFFIDAVIT-COMPLIANCE AFFIDAVIT ... AS PER COURT ORDER DATED 6\/8\/2019"},{"diary_no":320122019,"reg_no_display":"MA 521-523\/2020 in Crl.A. No. 376-378\/2004","pet_name":"STATE (GOVT. OF N.C.T. OF DELHI)","res_name":"SYED ABDUL REHMAN GILLANI","pno":1,"rno":1,"next_date":"","doc_number":"134703\/2019","doc_filing_date":"2019-09-03 11:15:42","doc_title":"VAKALATNAMA AND MEMO OF APPEARANCE-"},{"diary_no":322002019,"reg_no_display":"SLP(Crl) No. 8111\/2019","pet_name":"ADVANTAGE INDIA","res_name":"UNION OF INDIA","pno":2,"rno":3,"next_date":"","doc_number":"137072\/2019","doc_filing_date":"2019-09-05 15:59:47","doc_title":"PROOF OF SERVICE-CAVEAT PROOF"},{"diary_no":288172019,"reg_no_display":"W.P.(C) No. 1031\/2019","pet_name":"ANURADHA BHASIN","res_name":"UNION OF INDIA","pno":1,"rno":4,"next_date":"","doc_number":"135743\/2019","doc_filing_date":"2019-09-04 12:18:02","doc_title":"VAKALATNAMA AND MEMO OF APPEARANCE-"},{"diary_no":288172019,"reg_no_display":"W.P.(C) No. 1031\/2019","pet_name":"ANURADHA BHASIN","res_name":"UNION OF INDIA","pno":1,"rno":4,"next_date":"","doc_number":"135921\/2019","doc_filing_date":"2019-09-04 14:16:27","doc_title":"ADDITIONAL AFFIDAVIT-AS PER PERMISSION BY CM CT 3"},{"diary_no":288172019,"reg_no_display":"W.P.(C) No. 1031\/2019","pet_name":"ANURADHA BHASIN","res_name":"UNION OF INDIA","pno":1,"rno":4,"next_date":"","doc_number":"136290\/2019","doc_filing_date":"2019-09-04 16:07:20","doc_title":"VAKALATNAMA AND MEMO OF APPEARANCE-"},{"diary_no":288172019,"reg_no_display":"W.P.(C) No. 1031\/2019","pet_name":"ANURADHA BHASIN","res_name":"UNION OF INDIA","pno":1,"rno":4,"next_date":"","doc_number":"137488\/2019","doc_filing_date":"2019-09-06 12:42:22","doc_title":"PROOF OF SERVICE-"},{"diary_no":323162019,"reg_no_display":"SLP(Crl) No. 8174\/2019","pet_name":"M\/S ADVANTAGE INDIA","res_name":"UNION OF INDIA","pno":5,"rno":5,"next_date":"","doc_number":"137476\/2019","doc_filing_date":"2019-09-06 12:40:19","doc_title":"PROOF OF SERVICE-CAVEAT PROOF"},{"diary_no":224442019,"reg_no_display":"SLP(C) No. 16675\/2019","pet_name":"GREEN PARK ASSOCIATION (REGD)","res_name":"SOUTH DELHI MUNICIPAL CORPORATION","pno":1,"rno":4,"next_date":"2020-05-11","doc_number":"135256\/2019","doc_filing_date":"2019-09-03 15:10:45","doc_title":"VAKALATNAMA AND MEMO OF APPEARANCE-"},{"diary_no":280552019,"reg_no_display":"W.P.(C) No. 1013\/2019","pet_name":"MANOHAR LAL SHARMA","res_name":"UNION OF INDIA","pno":1,"rno":2,"next_date":"","doc_number":"135745\/2019","doc_filing_date":"2019-09-04 12:20:30","doc_title":"VAKALATNAMA AND MEMO OF APPEARANCE-"},{"diary_no":280552019,"reg_no_display":"W.P.(C) No. 1013\/2019","pet_name":"MANOHAR LAL SHARMA","res_name":"UNION OF INDIA","pno":1,"rno":2,"next_date":"","doc_number":"136291\/2019","doc_filing_date":"2019-09-04 16:07:33","doc_title":"VAKALATNAMA AND MEMO OF APPEARANCE-"},{"diary_no":297962019,"reg_no_display":"W.P.(C) No. 1099\/2019","pet_name":"SHAH FAESAL","res_name":"UNION OF INDIA","pno":8,"rno":2,"next_date":"","doc_number":"133932\/2019","doc_filing_date":"2019-09-02 11:09:54","doc_title":"PROCESS FEE-"},{"diary_no":297962019,"reg_no_display":"W.P.(C) No. 1099\/2019","pet_name":"SHAH FAESAL","res_name":"UNION OF INDIA","pno":8,"rno":2,"next_date":"","doc_number":"136348\/2019","doc_filing_date":"2019-09-04 16:25:35","doc_title":"VAKALATNAMA AND MEMO OF APPEARANCE-"},{"diary_no":297962019,"reg_no_display":"W.P.(C) No. 1099\/2019","pet_name":"SHAH FAESAL","res_name":"UNION OF INDIA","pno":8,"rno":2,"next_date":"","doc_number":"138061\/2019","doc_filing_date":"2019-09-06 16:04:11","doc_title":"VAKALATNAMA AND MEMO OF APPEARANCE-"},{"diary_no":285632019,"reg_no_display":"W.P.(C) No. 1048\/2019","pet_name":"SHAKIR SHABIR","res_name":"UNION OF INDIA","pno":1,"rno":3,"next_date":"","doc_number":"136355\/2019","doc_filing_date":"2019-09-04 16:28:48","doc_title":"VAKALATNAMA AND MEMO OF APPEARANCE-"},{"diary_no":285632019,"reg_no_display":"W.P.(C) No. 1048\/2019","pet_name":"SHAKIR SHABIR","res_name":"UNION OF INDIA","pno":1,"rno":3,"next_date":"","doc_number":"138048\/2019","doc_filing_date":"2019-09-06 15:58:29","doc_title":"VAKALATNAMA AND MEMO OF APPEARANCE-"},{"diary_no":296062019,"reg_no_display":"W.P.(C) No. 1070\/2019","pet_name":"RADHA KUMAR","res_name":"UNION OF INDIA","pno":6,"rno":2,"next_date":"","doc_number":"134073\/2019","doc_filing_date":"2019-09-02 12:27:22","doc_title":"PROCESS FEE-"},{"diary_no":296062019,"reg_no_display":"W.P.(C) No. 1070\/2019","pet_name":"RADHA KUMAR","res_name":"UNION OF INDIA","pno":6,"rno":2,"next_date":"","doc_number":"135874\/2019","doc_filing_date":"2019-09-04 14:03:36","doc_title":"PROOF OF SERVICE-"},{"diary_no":296062019,"reg_no_display":"W.P.(C) No. 1070\/2019","pet_name":"RADHA KUMAR","res_name":"UNION OF INDIA","pno":6,"rno":2,"next_date":"","doc_number":"136312\/2019","doc_filing_date":"2019-09-04 16:14:05","doc_title":"VAKALATNAMA AND MEMO OF APPEARANCE-"},{"diary_no":296062019,"reg_no_display":"W.P.(C) No. 1070\/2019","pet_name":"RADHA KUMAR","res_name":"UNION OF INDIA","pno":6,"rno":2,"next_date":"","doc_number":"138054\/2019","doc_filing_date":"2019-09-06 16:01:13","doc_title":"VAKALATNAMA AND MEMO OF APPEARANCE-"},{"diary_no":240332019,"reg_no_display":"SLP(C) No. 16845\/2019","pet_name":"APOORVA DABAS","res_name":"GOVT. OF NCT OF DELHI","pno":8,"rno":10,"next_date":"","doc_number":"137873\/2019","doc_filing_date":"2019-09-06 15:01:46","doc_title":"VAKALATNAMA AND MEMO OF APPEARANCE-"},{"diary_no":288192019,"reg_no_display":"W.P.(Crl.) No. 225\/2019","pet_name":"MOHAMMAD ALEEM SYED","res_name":"UNION OF INDIA","pno":1,"rno":1,"next_date":"","doc_number":"138060\/2019","doc_filing_date":"2019-09-06 16:03:11","doc_title":"VAKALATNAMA AND MEMO OF APPEARANCE-"},{"diary_no":297472019,"reg_no_display":"W.P.(Crl.) No. 229\/2019","pet_name":"SITARAM YECHURY","res_name":"UNION OF INDIA","pno":1,"rno":2,"next_date":"","doc_number":"134189\/2019","doc_filing_date":"2019-09-02 14:07:13","doc_title":"AFFIDAVIT-AFFIDAVIT ON BEHALF OF THE PETITIONER PURSUANT TO THE ORDER DT. 28.08.2019"},{"diary_no":297472019,"reg_no_display":"W.P.(Crl.) No. 229\/2019","pet_name":"SITARAM YECHURY","res_name":"UNION OF INDIA","pno":1,"rno":2,"next_date":"","doc_number":"138045\/2019","doc_filing_date":"2019-09-06 15:56:48","doc_title":"VAKALATNAMA AND MEMO OF APPEARANCE-"},{"diary_no":297472019,"reg_no_display":"W.P.(Crl.) No. 229\/2019","pet_name":"SITARAM YECHURY","res_name":"UNION OF INDIA","pno":1,"rno":2,"next_date":"","doc_number":"138063\/2019","doc_filing_date":"2019-09-06 16:05:29","doc_title":"PROCESS FEE-"},{"diary_no":286812019,"reg_no_display":"W.P.(C) No. 1068\/2019","pet_name":"SOAYIB QURESHI","res_name":"UNION OF INDIA","pno":1,"rno":3,"next_date":"","doc_number":"135252\/2019","doc_filing_date":"2019-09-03 15:08:52","doc_title":"PROCESS FEE-"},{"diary_no":286812019,"reg_no_display":"W.P.(C) No. 1068\/2019","pet_name":"SOAYIB QURESHI","res_name":"UNION OF INDIA","pno":1,"rno":3,"next_date":"","doc_number":"136302\/2019","doc_filing_date":"2019-09-04 16:11:10","doc_title":"VAKALATNAMA AND MEMO OF APPEARANCE-"},{"diary_no":290012019,"reg_no_display":"W.P.(C) No. 1062\/2019","pet_name":"INDER SALIM ALIAS INDER JI TICKOO","res_name":"UNION OF INDIA","pno":2,"rno":3,"next_date":"","doc_number":"134076\/2019","doc_filing_date":"2019-09-02 12:28:42","doc_title":"PROCESS FEE-SPARE COPIES"},{"diary_no":290012019,"reg_no_display":"W.P.(C) No. 1062\/2019","pet_name":"INDER SALIM ALIAS INDER JI TICKOO","res_name":"UNION OF INDIA","pno":2,"rno":3,"next_date":"","doc_number":"136343\/2019","doc_filing_date":"2019-09-04 16:24:58","doc_title":"VAKALATNAMA AND MEMO OF APPEARANCE-"},{"diary_no":309452019,"reg_no_display":"W.P.(C) No. 1104\/2019","pet_name":"MUZZAFAR IQBAL KHAN","res_name":"UNION OF INDIA","pno":1,"rno":3,"next_date":"","doc_number":"134154\/2019","doc_filing_date":"2019-09-02 12:50:18","doc_title":"PROCESS FEE-"},{"diary_no":309452019,"reg_no_display":"W.P.(C) No. 1104\/2019","pet_name":"MUZZAFAR IQBAL KHAN","res_name":"UNION OF INDIA","pno":1,"rno":3,"next_date":"","doc_number":"136309\/2019","doc_filing_date":"2019-09-04 16:13:33","doc_title":"VAKALATNAMA AND MEMO OF APPEARANCE-"},{"diary_no":288032019,"reg_no_display":"W.P.(C) No. 1037\/2019","pet_name":"MOHD. AKBAR LONE","res_name":"UNION OF INDIA","pno":2,"rno":3,"next_date":"","doc_number":"134163\/2019","doc_filing_date":"2019-09-02 12:52:04","doc_title":"PROCESS FEE-"},{"diary_no":288032019,"reg_no_display":"W.P.(C) No. 1037\/2019","pet_name":"MOHD. AKBAR LONE","res_name":"UNION OF INDIA","pno":2,"rno":3,"next_date":"","doc_number":"136354\/2019","doc_filing_date":"2019-09-04 16:28:36","doc_title":"VAKALATNAMA AND MEMO OF APPEARANCE-"},{"diary_no":285202019,"reg_no_display":"W.P.(C) No. 1082\/2019","pet_name":"FAROOQ AHMAD DAR","res_name":"UNION OF INDIA","pno":1,"rno":4,"next_date":"","doc_number":"136296\/2019","doc_filing_date":"2019-09-04 16:10:14","doc_title":"VAKALATNAMA AND MEMO OF APPEARANCE-"},{"diary_no":325892018,"reg_no_display":"W.P.(C) No. 1377\/2018","pet_name":"MANVIR SINGH","res_name":"UNION OF INDIA","pno":1,"rno":33,"next_date":"2020-04-09","doc_number":"135102\/2019","doc_filing_date":"2019-09-03 14:25:12","doc_title":"COUNTER AFFIDAVIT-"},{"diary_no":241642019,"reg_no_display":"W.P.(Crl.) No. 186\/2019","pet_name":"MOHD. AIJAZ AKBAR","res_name":"THE STATE OF RAJASTHAN","pno":1,"rno":4,"next_date":"","doc_number":"134878\/2019","doc_filing_date":"2019-09-03 12:13:07","doc_title":"AFFIDAVIT OF SERVICE-AFF.  OF DASTI SERVICE"},{"diary_no":290932017,"reg_no_display":"W.P.(C) No. 984\/2017","pet_name":"INSTITUTE OF DEMOCRACY AND SUSTAINABILITY","res_name":"UNION OF INDIA","pno":4,"rno":34,"next_date":"2020-05-14","doc_number":"135901\/2019","doc_filing_date":"2019-09-04 14:10:39","doc_title":"VAKALATNAMA AND MEMO OF APPEARANCE-"},{"diary_no":208722019,"reg_no_display":"W.P.(C) No. 819\/2019","pet_name":"BHAVIKA","res_name":"UNION OF INDIA","pno":1,"rno":36,"next_date":"","doc_number":"136528\/2019","doc_filing_date":"2019-09-05 11:33:36","doc_title":"COUNTER AFFIDAVIT-"},{"diary_no":208722019,"reg_no_display":"W.P.(C) No. 819\/2019","pet_name":"BHAVIKA","res_name":"UNION OF INDIA","pno":1,"rno":36,"next_date":"","doc_number":"137262\/2019","doc_filing_date":"2019-09-06 10:44:43","doc_title":"VAKALATNAMA AND MEMO OF APPEARANCE-"},{"diary_no":208722019,"reg_no_display":"W.P.(C) No. 819\/2019","pet_name":"BHAVIKA","res_name":"UNION OF INDIA","pno":1,"rno":36,"next_date":"","doc_number":"137753\/2019","doc_filing_date":"2019-09-06 14:37:02","doc_title":"VAKALATNAMA AND MEMO OF APPEARANCE-"},{"diary_no":260992019,"reg_no_display":"SLP(Crl) No. 6921\/2019","pet_name":"MEHBOOB ALI","res_name":"UNION OF INDIA","pno":1,"rno":3,"next_date":"","doc_number":"134270\/2019","doc_filing_date":"2019-09-02 14:31:38","doc_title":"PROCESS FEE-"},{"diary_no":308542019,"reg_no_display":"SLP(Crl) No. 7780\/2019","pet_name":"MRS. ANNU SHARMA","res_name":"THE STATE OF DELHI","pno":1,"rno":2,"next_date":"2020-04-14","doc_number":"137323\/2019","doc_filing_date":"2019-09-06 11:34:16","doc_title":"PROCESS FEE-"},{"diary_no":352352018,"reg_no_display":"SLP(C) No. 19600\/2019","pet_name":"POONAM SHARMA","res_name":"UNION OF INDIA","pno":3,"rno":6,"next_date":"","doc_number":"135599\/2019","doc_filing_date":"2019-09-04 11:08:34","doc_title":"PROCESS FEE-"},{"diary_no":237522019,"reg_no_display":"SLP(Crl) No. 6423-6424\/2019","pet_name":"PIYUSH GUPTA","res_name":"STATE NCT OF DELHI","pno":1,"rno":2,"next_date":"2020-04-13","doc_number":"135629\/2019","doc_filing_date":"2019-09-04 11:25:23","doc_title":"VAKALATNAMA AND MEMO OF APPEARANCE-"},{"diary_no":307082019,"reg_no_display":"W.P.(C) No. 1105\/2019","pet_name":"AMOL PAWAR","res_name":"UNION OF INDIA","pno":1,"rno":23,"next_date":"2020-04-13","doc_number":"134740\/2019","doc_filing_date":"2019-09-03 11:31:08","doc_title":"PROCESS FEE-"},{"diary_no":307082019,"reg_no_display":"W.P.(C) No. 1105\/2019","pet_name":"AMOL PAWAR","res_name":"UNION OF INDIA","pno":1,"rno":23,"next_date":"2020-04-13","doc_number":"136506\/2019","doc_filing_date":"2019-09-05 11:25:46","doc_title":"PROCESS FEE-"},{"diary_no":222982019,"reg_no_display":"SLP(Crl) No. 8138\/2019","pet_name":"JAI PARKASH","res_name":"STATE OF NCT OF DELHI","pno":1,"rno":1,"next_date":"","doc_number":"135087\/2019","doc_filing_date":"2019-09-03 14:19:43","doc_title":"PROOF OF SURRENDER\/CUSTODY CERTIFICATE-PROOF OF SURRENDER"},{"diary_no":221492019,"reg_no_display":"Crl.A. No. 1337\/2019","pet_name":"NARESH KUMAR","res_name":"STATE OF NCT OF DELHI","pno":1,"rno":2,"next_date":"","doc_number":"135175\/2019","doc_filing_date":"2019-09-03 14:46:10","doc_title":"PROOF OF SURRENDER\/CUSTODY CERTIFICATE-SURRENDER PROOF (TRUE COPY OF ORDER DATED 02.09.2019)"},{"diary_no":233132019,"reg_no_display":"W.P.(C) No. 924\/2019","pet_name":"GAURAV KUMAR BANSAL","res_name":"UNION OF INDIA","pno":1,"rno":38,"next_date":"2020-04-20","doc_number":"135251\/2019","doc_filing_date":"2019-09-03 15:08:43","doc_title":"PROOF OF SERVICE-PROOF OF SERVICE TO CENTRAL AGENCY FILED"}],"cases.disposed.787.2019-09-01_to_2019-09-07":[{"diary_no":252282019,"reg_no_display":"SLP(C) No. 21211-21212\/2019","pet_name":"UNION OF INDIA","res_name":"TANAKA RAM","pno":3,"rno":52,"next_date":"","disposal_date":"2019-09-02"},{"diary_no":274622019,"reg_no_display":"SLP(C) No. 21215\/2019","pet_name":"UNION OF INDIA","res_name":"041664366 CT\/GD BICHITRA SARMAH","pno":6,"rno":1,"next_date":"","disposal_date":"2019-09-02"},{"diary_no":279582019,"reg_no_display":"","pet_name":"UNION OF INDIA","res_name":"K. DEVAKI","pno":1,"rno":3,"next_date":"","disposal_date":"2019-09-02"},{"diary_no":132442018,"reg_no_display":"","pet_name":"STATE (NCT OF DELHI)","res_name":"NAVJOT SANDHU @ AFSAN GURU","pno":1,"rno":1,"next_date":"","disposal_date":"2019-09-04"},{"diary_no":397022011,"reg_no_display":"C.A. No. 2259\/2012","pet_name":"BACHCHAN PRASAD","res_name":"UNION OF INDIA .","pno":1,"rno":3,"next_date":"","disposal_date":"2019-09-04"},{"diary_no":204162011,"reg_no_display":"C.A. No. 7013\/2011","pet_name":"SAMJHANA CHETTRI","res_name":"UNION OF INDIA MINISTRY OF DEFENCE","pno":1,"rno":3,"next_date":"","disposal_date":"2019-09-04"},{"diary_no":227842014,"reg_no_display":"Crl.A. No. 967\/2015","pet_name":"JAGBIR SINGH","res_name":"STATE (NCT OF DELHI)","pno":1,"rno":1,"next_date":"","disposal_date":"2019-09-04"},{"diary_no":166622009,"reg_no_display":"C.A. No. 3134\/2010","pet_name":"DELHI MEDICAL ASSOCIATION","res_name":"UNION OF INDIA","pno":2,"rno":4,"next_date":"","disposal_date":"2019-09-03"},{"diary_no":439352018,"reg_no_display":"W.P.(Crl.) No. 326\/2018","pet_name":"KARTIK SUBRAMANIAM","res_name":"UNION OF INDIA","pno":1,"rno":3,"next_date":"","disposal_date":"2019-09-06"}],"cases.judgments.787.2019-09-01_to_2019-09-07":[{"diary_no":639981985,"reg_no_display":"W.P.(C) No. 13029\/1985","pet_name":"M.C. MEHTA","res_name":"UNION OF INDIA","pno":1,"rno":59,"next_date":"2020-04-07","order_date":"2019-09-02"},{"diary_no":227842014,"reg_no_display":"Crl.A. No. 967\/2015","pet_name":"JAGBIR SINGH","res_name":"STATE (NCT OF DELHI)","pno":1,"rno":1,"next_date":"","order_date":"2019-09-04"}],"cases.daily_orders.787.2019-09-01_to_2019-09-07":[{"diary_no":80832009,"reg_no_display":"SLP(C) No. 13466\/2009","pet_name":"UNION OF INDIA ","res_name":"TANWIR IQBAL(DEAD) BY LRS.","pno":3,"rno":3,"next_date":"2020-04-29","last_order_date":"2019-09-05"},{"diary_no":97522012,"reg_no_display":"C.A. No. 4714-4715\/2012","pet_name":"UNION OF INDIA","res_name":"V.R.NANUKUTTAN NAIR","pno":3,"rno":1,"next_date":"","last_order_date":"2019-09-04"},{"diary_no":114562012,"reg_no_display":"C.A. No. 4981\/2012","pet_name":"SECRETARY,GOVT.OF INDIA .","res_name":"DHARAMBIR SINGH","pno":3,"rno":1,"next_date":"","last_order_date":"2019-09-04"},{"diary_no":127382019,"reg_no_display":"","pet_name":"GOVT. OF NCT OF DELHI","res_name":"PREM KAUR","pno":1,"rno":7,"next_date":"","last_order_date":"2019-09-04"},{"diary_no":132442018,"reg_no_display":"","pet_name":"STATE (NCT OF DELHI)","res_name":"NAVJOT SANDHU @ AFSAN GURU","pno":1,"rno":1,"next_date":"","last_order_date":"2019-09-04"},{"diary_no":144002019,"reg_no_display":"C.A. No. 8259\/2019","pet_name":"GOVT. OF NCT DELHI","res_name":"PRADEEP KUMAR","pno":3,"rno":7,"next_date":"","last_order_date":"2019-09-03"},{"diary_no":150392019,"reg_no_display":"","pet_name":"UNION OF INDIA","res_name":"RAMPADA PANJA","pno":8,"rno":6,"next_date":"","last_order_date":"2019-09-06"},{"diary_no":235002015,"reg_no_display":"C.A. No. 6227-6236\/2016","pet_name":"COMMISSIONER OF TRADE AND TAXES","res_name":"M\/S ANAND DECORS  ETC","pno":1,"rno":1,"next_date":"","last_order_date":"2019-09-05"},{"diary_no":252282019,"reg_no_display":"SLP(C) No. 21211-21212\/2019","pet_name":"UNION OF INDIA","res_name":"TANAKA RAM","pno":3,"rno":52,"next_date":"","last_order_date":"2019-09-02"},{"diary_no":265662017,"reg_no_display":"SLP(C) No. 25860\/2017","pet_name":"UNION OF INDIA","res_name":"INDU BHUSAN JANA (DEAD THR LR)","pno":3,"rno":7,"next_date":"","last_order_date":"2019-09-06"},{"diary_no":274622019,"reg_no_display":"SLP(C) No. 21215\/2019","pet_name":"UNION OF INDIA","res_name":"041664366 CT\/GD BICHITRA SARMAH","pno":6,"rno":1,"next_date":"","last_order_date":"2019-09-02"},{"diary_no":279582019,"reg_no_display":"","pet_name":"UNION OF INDIA","res_name":"K. DEVAKI","pno":1,"rno":3,"next_date":"","last_order_date":"2019-09-02"},{"diary_no":319732018,"reg_no_display":"C.A. No. 9109\/2019","pet_name":"UNION OF INDIA","res_name":"RAMESH BISHNOI","pno":4,"rno":1,"next_date":"","last_order_date":"2019-09-06"},{"diary_no":324472018,"reg_no_display":"SLP(Crl) No. 1765\/2019","pet_name":"THE STATE OF JHARKHAND","res_name":"LODORO MUNDA","pno":1,"rno":1,"next_date":"2020-05-14","last_order_date":"2019-09-06"},{"diary_no":4642012,"reg_no_display":"C.A. No. 190-191\/2013","pet_name":"TEJA SINGH","res_name":"UOI","pno":1,"rno":5,"next_date":"","last_order_date":"2019-09-04"},{"diary_no":16992019,"reg_no_display":"W.P.(C) No. 62\/2019","pet_name":"TRIPURA PEOPLES FRONT","res_name":"UNION OF INDIA","pno":1,"rno":3,"next_date":"2020-04-27","last_order_date":"2019-09-04"},{"diary_no":28402019,"reg_no_display":"SLP(Crl) No. 1027\/2019","pet_name":"SAURABH CHAUDHARY","res_name":"STATE OF NCT OF DELHI","pno":1,"rno":2,"next_date":"","last_order_date":"2019-09-06"},{"diary_no":80302017,"reg_no_display":"C.A. No. 6447\/2017","pet_name":"NORTH DELHI MUNICIPAL CORPORATION","res_name":"SPRINGDALES SCHOOL","pno":1,"rno":3,"next_date":"","last_order_date":"2019-09-05"},{"diary_no":144632018,"reg_no_display":"C.A. No. 11473-11474\/2018","pet_name":"AMARENDRA KUMAR PANDEY","res_name":"UNION OF INDIA","pno":1,"rno":4,"next_date":"","last_order_date":"2019-09-02"},{"diary_no":166622009,"reg_no_display":"C.A. No. 3134\/2010","pet_name":"DELHI MEDICAL ASSOCIATION","res_name":"UNION OF INDIA","pno":2,"rno":4,"next_date":"","last_order_date":"2019-09-03"},{"diary_no":202432018,"reg_no_display":"Crl.A. No. 415-417\/2019","pet_name":"KEKHRIESATUO TEP","res_name":"NATIONAL INVESTIGATION AGENCY","pno":3,"rno":1,"next_date":"","last_order_date":"2019-09-05"},{"diary_no":204162011,"reg_no_display":"C.A. No. 7013\/2011","pet_name":"SAMJHANA CHETTRI","res_name":"UNION OF INDIA MINISTRY OF DEFENCE","pno":1,"rno":3,"next_date":"","last_order_date":"2019-09-04"},{"diary_no":210242017,"reg_no_display":"MA 267\/2017 in SLP(Crl) No. 657\/2017","pet_name":"DILAWAR","res_name":"THE STATE OF HARYANA","pno":1,"rno":3,"next_date":"","last_order_date":"2019-09-06"},{"diary_no":222082019,"reg_no_display":"SLP(C) No. 16228\/2019","pet_name":"SARAJUDDIN ANSARI","res_name":"UNION OF INDIA","pno":1,"rno":5,"next_date":"","last_order_date":"2019-09-06"},{"diary_no":222732018,"reg_no_display":"C.A. No. 6431\/2019","pet_name":"KRUSHNAKANT B. PARMAR","res_name":"UNION OF INDIA","pno":1,"rno":2,"next_date":"","last_order_date":"2019-09-04"},{"diary_no":224442019,"reg_no_display":"SLP(C) No. 16675\/2019","pet_name":"GREEN PARK ASSOCIATION (REGD)","res_name":"SOUTH DELHI MUNICIPAL CORPORATION","pno":1,"rno":4,"next_date":"2020-05-11","last_order_date":"2019-09-03"},{"diary_no":227012011,"reg_no_display":"C.A. No. 297\/2012","pet_name":"UNION OF INDIA","res_name":"SHRI ONKAR SINGH","pno":3,"rno":1,"next_date":"","last_order_date":"2019-09-02"},{"diary_no":227842014,"reg_no_display":"Crl.A. No. 967\/2015","pet_name":"JAGBIR SINGH","res_name":"STATE (NCT OF DELHI)","pno":1,"rno":1,"next_date":"","last_order_date":"2019-09-04"},{"diary_no":232582019,"reg_no_display":"SLP(Crl) No. 6364\/2019","pet_name":"PRITI SARAF","res_name":"STATE OF NCT OF DELHI","pno":2,"rno":2,"next_date":"","last_order_date":"2019-09-04"},{"diary_no":233492019,"reg_no_display":"SLP(Crl) No. 6989\/2019","pet_name":"JITENDER  KUMAR","res_name":"STATE (NCT OF DELHI)","pno":1,"rno":1,"next_date":"","last_order_date":"2019-09-02"},{"diary_no":240332019,"reg_no_display":"SLP(C) No. 16845\/2019","pet_name":"APOORVA DABAS","res_name":"GOVT. OF NCT OF DELHI","pno":8,"rno":10,"next_date":"","last_order_date":"2019-09-06"},{"diary_no":259582009,"reg_no_display":"Crl.A. No. 2319-2320\/2009","pet_name":"NAJMUNISHA ETC.","res_name":"THE STATE OF GUJARAT ","pno":1,"rno":2,"next_date":"","last_order_date":"2019-09-05"},{"diary_no":267622019,"reg_no_display":"SLP(C) No. 21920\/2019","pet_name":"MEENAKSHI","res_name":"DELHI SUBORDINATE SERVICES SELECTION BOARD","pno":1,"rno":2,"next_date":"","last_order_date":"2019-09-06"},{"diary_no":271162019,"reg_no_display":"W.P.(Crl.) No. 224\/2019","pet_name":"SANJAY","res_name":"UNION OF INDIA","pno":1,"rno":2,"next_date":"2020-04-20","last_order_date":"2019-09-05"},{"diary_no":272842019,"reg_no_display":"SLP(Crl) No. 8864-8865\/2019","pet_name":"GOURI SHANKAR SHARMA","res_name":"STATE OF GNCT OF DELHI","pno":1,"rno":1,"next_date":"2020-04-13","last_order_date":"2019-09-06"},{"diary_no":288172019,"reg_no_display":"W.P.(C) No. 1031\/2019","pet_name":"ANURADHA BHASIN","res_name":"UNION OF INDIA","pno":1,"rno":4,"next_date":"","last_order_date":"2019-09-05"},{"diary_no":288192019,"reg_no_display":"W.P.(Crl.) No. 225\/2019","pet_name":"MOHAMMAD ALEEM SYED","res_name":"UNION OF INDIA","pno":1,"rno":1,"next_date":"","last_order_date":"2019-09-05"},{"diary_no":294942019,"reg_no_display":"W.P.(C) No. 1076\/2019","pet_name":"SAJAL AWASTHI","res_name":"UNION OF INDIA","pno":1,"rno":1,"next_date":"","last_order_date":"2019-09-06"},{"diary_no":295082018,"reg_no_display":"W.P.(Crl.) No. 191\/2018","pet_name":"ABCD","res_name":"UNION OF INDIA","pno":1,"rno":8,"next_date":"","last_order_date":"2019-09-06"},{"diary_no":297472019,"reg_no_display":"W.P.(Crl.) No. 229\/2019","pet_name":"SITARAM YECHURY","res_name":"UNION OF INDIA","pno":1,"rno":2,"next_date":"","last_order_date":"2019-09-05"},{"diary_no":304992018,"reg_no_display":"Crl.A. No. 878\/2019","pet_name":"AJAY KUMAR GUPTA","res_name":"UNION OF INDIA","pno":1,"rno":1,"next_date":"","last_order_date":"2019-09-02"},{"diary_no":308542019,"reg_no_display":"SLP(Crl) No. 7780\/2019","pet_name":"MRS. ANNU SHARMA","res_name":"THE STATE OF DELHI","pno":1,"rno":2,"next_date":"2020-04-14","last_order_date":"2019-09-06"},{"diary_no":327142015,"reg_no_display":"C.A. No. 9276-9290\/2015","pet_name":"TATA POWER DELHI DISTRIBUTION LTD. NDPL HOUSE","res_name":"MANOJ MISHRA AND ORS. ETC. ETC.","pno":1,"rno":3,"next_date":"","last_order_date":"2019-09-06"},{"diary_no":337112018,"reg_no_display":"W.P.(Crl.) No. 250\/2018","pet_name":"MOHAMMAD AFAQ KHAN","res_name":"THE STATE OF RAJASTHAN","pno":1,"rno":4,"next_date":"","last_order_date":"2019-09-04"},{"diary_no":369062012,"reg_no_display":"W.P.(Crl.) No. 159\/2012","pet_name":"BHARATI TAMANG","res_name":"UNION OF INDIA","pno":1,"rno":24,"next_date":"2020-05-04","last_order_date":"2019-09-02"},{"diary_no":397022011,"reg_no_display":"C.A. No. 2259\/2012","pet_name":"BACHCHAN PRASAD","res_name":"UNION OF INDIA .","pno":1,"rno":3,"next_date":"","last_order_date":"2019-09-04"},{"diary_no":439352018,"reg_no_display":"W.P.(Crl.) No. 326\/2018","pet_name":"KARTIK SUBRAMANIAM","res_name":"UNION OF INDIA","pno":1,"rno":3,"next_date":"","last_order_date":"2019-09-06"},{"diary_no":639981985,"reg_no_display":"W.P.(C) No. 13029\/1985","pet_name":"M.C. MEHTA","res_name":"UNION OF INDIA","pno":1,"rno":59,"next_date":"2020-04-07","last_order_date":"2019-09-06"}],"cases.certified_copies.787.2019-09-01_to_2019-09-07":[{"diary_no":133922019,"reg_no_display":"SLP(Crl) No. 7229\/2019","pet_name":"SHIVA RATHAUR","res_name":"UNION OF INDIA","pno":1,"rno":2,"next_date":"","applied_date":"2019-09-03 15:50:45","ready_date":null,"delivery_date":"2019-09-17 16:17:20","filed_by":"S. R. SETIA","applied_of":"Proceedings-2019-08-13 00:00:00#"},{"diary_no":221492019,"reg_no_display":"Crl.A. No. 1337\/2019","pet_name":"NARESH KUMAR","res_name":"STATE OF NCT OF DELHI","pno":1,"rno":2,"next_date":"","applied_date":"2019-09-03 15:17:11","ready_date":null,"delivery_date":"2019-09-05 12:36:51","filed_by":"SHWETANK SAILAKWAL","applied_of":"Signed Order-2019-08-19 00:00:00#"},{"diary_no":227842014,"reg_no_display":"Crl.A. No. 967\/2015","pet_name":"JAGBIR SINGH","res_name":"STATE (NCT OF DELHI)","pno":1,"rno":1,"next_date":"","applied_date":"2019-09-05 14:32:46","ready_date":null,"delivery_date":"2019-09-13 11:46:59","filed_by":"d b goswami","applied_of":"Judgment-2019-09-04 00:00:00#,Proceedings-2019-08-01 00:00:00#"},{"diary_no":233492019,"reg_no_display":"SLP(Crl) No. 6989\/2019","pet_name":"JITENDER  KUMAR","res_name":"STATE (NCT OF DELHI)","pno":1,"rno":1,"next_date":"","applied_date":"2019-09-02 17:06:28","ready_date":null,"delivery_date":"2019-09-05 11:01:24","filed_by":"PRASHANT KUMAR","applied_of":"Bail Order-2019-09-02 00:00:00#"},{"diary_no":233492019,"reg_no_display":"SLP(Crl) No. 6989\/2019","pet_name":"JITENDER  KUMAR","res_name":"STATE (NCT OF DELHI)","pno":1,"rno":1,"next_date":"","applied_date":"2019-09-03 11:23:41","ready_date":null,"delivery_date":"2019-09-05 16:25:00","filed_by":"PRASHANT KUMAR","applied_of":"Bail Order-2019-08-02 00:00:00#"},{"diary_no":246702017,"reg_no_display":"SLP(Crl) No. 5978-5979\/2017","pet_name":"SANJAY CHANDRA","res_name":"STATE GOVT. OF NCT OF DELHI","pno":3,"rno":6,"next_date":"2020-04-17","applied_date":"2019-09-04 12:28:12","ready_date":null,"delivery_date":"2019-09-05 16:26:37","filed_by":"E. C. AGRAWALA","applied_of":"Proceedings-2018-04-09 00:00:00#,Proceedings-2018-04-09 00:00:00#"},{"diary_no":252282019,"reg_no_display":"SLP(C) No. 21211-21212\/2019","pet_name":"UNION OF INDIA","res_name":"TANAKA RAM","pno":3,"rno":52,"next_date":"","applied_date":"2019-09-03 14:42:46","ready_date":null,"delivery_date":"2019-09-05 16:22:08","filed_by":"ANUPAM RAINA","applied_of":"Proceedings-2019-09-02 00:00:00#"},{"diary_no":260992019,"reg_no_display":"SLP(Crl) No. 6921\/2019","pet_name":"MEHBOOB ALI","res_name":"UNION OF INDIA","pno":1,"rno":3,"next_date":"","applied_date":"2019-09-02 14:47:20","ready_date":null,"delivery_date":"2019-09-05 11:59:18","filed_by":"SUDHIR NAAGAR","applied_of":"Proceedings-2019-08-30 00:00:00#"}],"cases.office_reports.787.2019-09-01_to_2019-09-07":[{"diary_no":246702017,"reg_no_display":"SLP(Crl) No. 5978-5979\/2017","pet_name":"SANJAY CHANDRA","res_name":"STATE GOVT. OF NCT OF DELHI","pno":3,"rno":6,"next date":"2020-04-17"},{"diary_no":639981985,"reg_no_display":"W.P.(C) No. 13029\/1985","pet_name":"M.C. MEHTA","res_name":"UNION OF INDIA","pno":1,"rno":59,"next date":"2020-04-07"},{"diary_no":32572018,"reg_no_display":"SLP(C) No. 6914-6915\/2018","pet_name":"RAJINDER SINGH","res_name":"UNION OF INDIA","pno":1,"rno":4,"next date":"2020-05-11"},{"diary_no":202432018,"reg_no_display":"Crl.A. No. 415-417\/2019","pet_name":"KEKHRIESATUO TEP","res_name":"NATIONAL INVESTIGATION AGENCY","pno":3,"rno":1,"next date":""},{"diary_no":210242017,"reg_no_display":"MA 267\/2017 in SLP(Crl) No. 657\/2017","pet_name":"DILAWAR","res_name":"THE STATE OF HARYANA","pno":1,"rno":3,"next date":""},{"diary_no":300522018,"reg_no_display":"SLP(C) No. 28015-28017\/2018","pet_name":"UNION OF INDIA","res_name":"KANWAL SINGH","pno":5,"rno":1,"next date":"2020-05-14"},{"diary_no":222732018,"reg_no_display":"C.A. No. 6431\/2019","pet_name":"KRUSHNAKANT B. PARMAR","res_name":"UNION OF INDIA","pno":1,"rno":2,"next date":""},{"diary_no":324472018,"reg_no_display":"SLP(Crl) No. 1765\/2019","pet_name":"THE STATE OF JHARKHAND","res_name":"LODORO MUNDA","pno":1,"rno":1,"next date":"2020-05-14"},{"diary_no":337442018,"reg_no_display":"Crl.A. No. 418\/2019","pet_name":"G IKUTO ZHIMOMI","res_name":"NATIONAL INVESTIGATION AGENCY","pno":1,"rno":1,"next date":""},{"diary_no":79522019,"reg_no_display":"C.A. No. 5246\/2019","pet_name":"COMMISSIONER OF GST AND CENTRAL EXCISE CHENNAI","res_name":"MAHINDRA HOLIDAY AND RESORTS INDIA LTD","pno":1,"rno":1,"next date":"2020-04-21"},{"diary_no":127382019,"reg_no_display":"","pet_name":"GOVT. OF NCT OF DELHI","res_name":"PREM KAUR","pno":1,"rno":7,"next date":""},{"diary_no":16992019,"reg_no_display":"W.P.(C) No. 62\/2019","pet_name":"TRIPURA PEOPLES FRONT","res_name":"UNION OF INDIA","pno":1,"rno":3,"next date":"2020-04-27"},{"diary_no":439352018,"reg_no_display":"W.P.(Crl.) No. 326\/2018","pet_name":"KARTIK SUBRAMANIAM","res_name":"UNION OF INDIA","pno":1,"rno":3,"next date":""},{"diary_no":144002019,"reg_no_display":"C.A. No. 8259\/2019","pet_name":"GOVT. OF NCT DELHI","res_name":"PRADEEP KUMAR","pno":3,"rno":7,"next date":""},{"diary_no":150392019,"reg_no_display":"","pet_name":"UNION OF INDIA","res_name":"RAMPADA PANJA","pno":8,"rno":6,"next date":""},{"diary_no":247442019,"reg_no_display":"SLP(C) No. 21801\/2019","pet_name":"THE COMMISSIONER OF POLICE","res_name":"KIRPAL SINGH","pno":4,"rno":1,"next date":""},{"diary_no":309272018,"reg_no_display":"SLP(Crl) No. 1573\/2019","pet_name":"JASVINDER SINGH @KOOKI","res_name":"UNION OF INDIA","pno":1,"rno":1,"next date":""},{"diary_no":68942019,"reg_no_display":"SLP(C) No. 7753\/2019","pet_name":"DALIT PRAHARI","res_name":"GOVT. OF NCT OF DELHI","pno":12,"rno":3,"next date":""},{"diary_no":322002019,"reg_no_display":"SLP(Crl) No. 8111\/2019","pet_name":"ADVANTAGE INDIA","res_name":"UNION OF INDIA","pno":2,"rno":3,"next date":""},{"diary_no":288172019,"reg_no_display":"W.P.(C) No. 1031\/2019","pet_name":"ANURADHA BHASIN","res_name":"UNION OF INDIA","pno":1,"rno":4,"next date":""},{"diary_no":323162019,"reg_no_display":"SLP(Crl) No. 8174\/2019","pet_name":"M\/S ADVANTAGE INDIA","res_name":"UNION OF INDIA","pno":5,"rno":5,"next date":""},{"diary_no":226612019,"reg_no_display":"SLP(Crl) No. 5489-5490\/2019","pet_name":"JOSE C. MUNDADAN","res_name":"GOVT OF NCT OF DELHI","pno":1,"rno":2,"next date":""},{"diary_no":240332019,"reg_no_display":"SLP(C) No. 16845\/2019","pet_name":"APOORVA DABAS","res_name":"GOVT. OF NCT OF DELHI","pno":8,"rno":10,"next date":""},{"diary_no":288192019,"reg_no_display":"W.P.(Crl.) No. 225\/2019","pet_name":"MOHAMMAD ALEEM SYED","res_name":"UNION OF INDIA","pno":1,"rno":1,"next date":""},{"diary_no":297472019,"reg_no_display":"W.P.(Crl.) No. 229\/2019","pet_name":"SITARAM YECHURY","res_name":"UNION OF INDIA","pno":1,"rno":2,"next date":""},{"diary_no":267622019,"reg_no_display":"SLP(C) No. 21920\/2019","pet_name":"MEENAKSHI","res_name":"DELHI SUBORDINATE SERVICES SELECTION BOARD","pno":1,"rno":2,"next date":""},{"diary_no":232582019,"reg_no_display":"SLP(Crl) No. 6364\/2019","pet_name":"PRITI SARAF","res_name":"STATE OF NCT OF DELHI","pno":2,"rno":2,"next date":""},{"diary_no":226542019,"reg_no_display":"SLP(C) No. 26697\/2019","pet_name":"DELHI DEVELOPMENT AUTHORITY","res_name":"TEJPAL","pno":1,"rno":4,"next date":"2020-04-17"},{"diary_no":222082019,"reg_no_display":"SLP(C) No. 16228\/2019","pet_name":"SARAJUDDIN ANSARI","res_name":"UNION OF INDIA","pno":1,"rno":5,"next date":""},{"diary_no":271162019,"reg_no_display":"W.P.(Crl.) No. 224\/2019","pet_name":"SANJAY","res_name":"UNION OF INDIA","pno":1,"rno":2,"next date":"2020-04-20"}],"cases.caveat.787.2019-09-01_to_2019-09-07":[],"cases.ia.787.2019-09-01_to_2019-09-07":[{"diary_no":639981985,"reg_no_display":"W.P.(C) No. 13029\/1985","pet_name":"M.C. MEHTA","res_name":"UNION OF INDIA","pno":1,"rno":59,"next_date":"2020-04-07","doc_number":"137447\/2019","doc_filing_date":"2019-09-06 12:34:44","doc_title":"INTERVENTION\/IMPLEADMENT-AN APPLICATION FOR IMPLEADMENT. PER BY CM COURT NO. 4"},{"diary_no":639981985,"reg_no_display":"W.P.(C) No. 13029\/1985","pet_name":"M.C. MEHTA","res_name":"UNION OF INDIA","pno":1,"rno":59,"next_date":"2020-04-07","doc_number":"137452\/2019","doc_filing_date":"2019-09-06 12:36:08","doc_title":"CLARIFICATION\/DIRECTION-AN APPLICATION FOR DIRECTION AS PER BY CM CT. NO. 4"},{"diary_no":639981985,"reg_no_display":"W.P.(C) No. 13029\/1985","pet_name":"M.C. MEHTA","res_name":"UNION OF INDIA","pno":1,"rno":59,"next_date":"2020-04-07","doc_number":"137922\/2019","doc_filing_date":"2019-09-06 15:19:27","doc_title":"INTERVENTION APPLICATION-"},{"diary_no":319732018,"reg_no_display":"C.A. No. 9109\/2019","pet_name":"UNION OF INDIA","res_name":"RAMESH BISHNOI","pno":4,"rno":1,"next_date":"","doc_number":"136457\/2019","doc_filing_date":"2019-09-05 10:54:50","doc_title":"PERMISSION TO FILE ADDITIONAL DOCUMENTS\/FACTS\/ANNEXURES-"},{"diary_no":319732018,"reg_no_display":"C.A. No. 9109\/2019","pet_name":"UNION OF INDIA","res_name":"RAMESH BISHNOI","pno":4,"rno":1,"next_date":"","doc_number":"136459\/2019","doc_filing_date":"2019-09-05 10:55:07","doc_title":"EXEMPTION FROM FILING O.T.-"},{"diary_no":179102019,"reg_no_display":"","pet_name":"UNION OF INDIA","res_name":"ABHISHEK THIMMAIAH","pno":1,"rno":1,"next_date":"","doc_number":"137037\/2019","doc_filing_date":"2019-09-05 15:50:00","doc_title":"PERMISSION TO FILE ADDITIONAL DOCUMENTS\/FACTS\/ANNEXURES-APPLICATION FOR PLACING ON RECORD ADDITIONAL FACTS, EVENTS AND DOCUMENTS"},{"diary_no":220952019,"reg_no_display":"","pet_name":"UNION OF INDIA","res_name":"SRI ANANTA KUMAR JANA (D)","pno":3,"rno":3,"next_date":"","doc_number":"135692\/2019","doc_filing_date":"2019-09-04 11:53:38","doc_title":"CONDONATION OF DELAY IN FILING SUBSTITUTION APPLN.-"},{"diary_no":281872019,"reg_no_display":"SLP(C) No. 22079\/2019","pet_name":"UNION OF INDIA","res_name":"SHAM SINGH","pno":2,"rno":1,"next_date":"","doc_number":"135524\/2019","doc_filing_date":"2019-09-03 17:57:26","doc_title":"CONDONATION OF DELAY IN FILING-"},{"diary_no":290322019,"reg_no_display":"Crl.A. No. 1416-1419\/2019","pet_name":"STATE (NCT OF DELHI)","res_name":"MANOJ","pno":1,"rno":2,"next_date":"","doc_number":"138497\/2019","doc_filing_date":"2019-09-07 12:51:06","doc_title":"CONDONATION OF DELAY IN FILING-"},{"diary_no":290322019,"reg_no_display":"Crl.A. No. 1416-1419\/2019","pet_name":"STATE (NCT OF DELHI)","res_name":"MANOJ","pno":1,"rno":2,"next_date":"","doc_number":"138498\/2019","doc_filing_date":"2019-09-07 12:51:20","doc_title":"EXEMPTION FROM FILING O.T.-"},{"diary_no":290322019,"reg_no_display":"Crl.A. No. 1416-1419\/2019","pet_name":"STATE (NCT OF DELHI)","res_name":"MANOJ","pno":1,"rno":2,"next_date":"","doc_number":"138499\/2019","doc_filing_date":"2019-09-07 12:51:37","doc_title":"PERMISSION TO FILE LENGTHY LIST OF DATES-"},{"diary_no":302882019,"reg_no_display":"SLP(Crl) No. 8654\/2019","pet_name":"STATE (GOVT. OF NCT OF DELHI)","res_name":"HARVINDER SINGH @ RAJU","pno":1,"rno":1,"next_date":"","doc_number":"136744\/2019","doc_filing_date":"2019-09-05 13:41:38","doc_title":"CONDONATION OF DELAY IN FILING-"},{"diary_no":302882019,"reg_no_display":"SLP(Crl) No. 8654\/2019","pet_name":"STATE (GOVT. OF NCT OF DELHI)","res_name":"HARVINDER SINGH @ RAJU","pno":1,"rno":1,"next_date":"","doc_number":"136745\/2019","doc_filing_date":"2019-09-05 13:42:11","doc_title":"EXEMPTION FROM FILING C\/C OF THE IMPUGNED JUDGMENT-"},{"diary_no":307672019,"reg_no_display":"","pet_name":"NARCOTICS CONTROL BUREAU","res_name":"KISHORI LAL RANA @ SANJU","pno":1,"rno":1,"next_date":"","doc_number":"137784\/2019","doc_filing_date":"2019-09-06 14:42:50","doc_title":"CONDONATION OF DELAY IN FILING-"},{"diary_no":307672019,"reg_no_display":"","pet_name":"NARCOTICS CONTROL BUREAU","res_name":"KISHORI LAL RANA @ SANJU","pno":1,"rno":1,"next_date":"","doc_number":"137787\/2019","doc_filing_date":"2019-09-06 14:43:00","doc_title":"EXEMPTION FROM FILING C\/C OF THE IMPUGNED JUDGMENT-"},{"diary_no":312792019,"reg_no_display":"SLP(C) No. 22336\/2019","pet_name":"UNION OF INDIA","res_name":"CONSTABLE UMA SHANKARAN","pno":3,"rno":1,"next_date":"","doc_number":"138180\/2019","doc_filing_date":"2019-09-07 10:16:24","doc_title":"CONDONATION OF DELAY IN FILING-"},{"diary_no":313902019,"reg_no_display":"SLP(C) No. 22804\/2019","pet_name":"UNION OF INDIA","res_name":"GHULAM HUSSAIN","pno":5,"rno":1,"next_date":"","doc_number":"137728\/2019","doc_filing_date":"2019-09-06 14:31:53","doc_title":"CONDONATION OF DELAY IN FILING APPEAL-"},{"diary_no":313902019,"reg_no_display":"SLP(C) No. 22804\/2019","pet_name":"UNION OF INDIA","res_name":"GHULAM HUSSAIN","pno":5,"rno":1,"next_date":"","doc_number":"137729\/2019","doc_filing_date":"2019-09-06 14:32:17","doc_title":"EXEMPTION FROM FILING C\/C OF THE IMPUGNED JUDGMENT-"},{"diary_no":86402008,"reg_no_display":"W.P.(C) No. 109\/2008","pet_name":"WILDLIFE FIRST","res_name":"MINISTRY OF FOREST AND ENVIRONMENT","pno":3,"rno":17,"next_date":"","doc_number":"137518\/2019","doc_filing_date":"2019-09-06 12:47:56","doc_title":"EXEMPTION FROM FILING O.T.-"},{"diary_no":86402008,"reg_no_display":"W.P.(C) No. 109\/2008","pet_name":"WILDLIFE FIRST","res_name":"MINISTRY OF FOREST AND ENVIRONMENT","pno":3,"rno":17,"next_date":"","doc_number":"137888\/2019","doc_filing_date":"2019-09-06 15:09:30","doc_title":"EXEMPTION FROM PERSONAL APPEARANCE-"},{"diary_no":320122019,"reg_no_display":"MA 521-523\/2020 in Crl.A. No. 376-378\/2004","pet_name":"STATE (GOVT. OF N.C.T. OF DELHI)","res_name":"SYED ABDUL REHMAN GILLANI","pno":1,"rno":1,"next_date":"","doc_number":"134701\/2019","doc_filing_date":"2019-09-03 11:14:33","doc_title":"APPLICATION FOR PERMISSION-APPLICATION FOR PERMISSION TO FILE APPLICATION FOR DIRECTION. PER BY CM COURT NO. 3"},{"diary_no":320122019,"reg_no_display":"MA 521-523\/2020 in Crl.A. No. 376-378\/2004","pet_name":"STATE (GOVT. OF N.C.T. OF DELHI)","res_name":"SYED ABDUL REHMAN GILLANI","pno":1,"rno":1,"next_date":"","doc_number":"134707\/2019","doc_filing_date":"2019-09-03 11:16:22","doc_title":"CLARIFICATION\/DIRECTION-AN APPLICATION FOR DIRECTION"},{"diary_no":322002019,"reg_no_display":"SLP(Crl) No. 8111\/2019","pet_name":"ADVANTAGE INDIA","res_name":"UNION OF INDIA","pno":2,"rno":3,"next_date":"","doc_number":"136727\/2019","doc_filing_date":"2019-09-05 12:59:26","doc_title":"EXEMPTION FROM FILING C\/C OF THE IMPUGNED JUDGMENT-"},{"diary_no":288172019,"reg_no_display":"W.P.(C) No. 1031\/2019","pet_name":"ANURADHA BHASIN","res_name":"UNION OF INDIA","pno":1,"rno":4,"next_date":"","doc_number":"136292\/2019","doc_filing_date":"2019-09-04 16:07:55","doc_title":"INTERVENTION\/IMPLEADMENT-AN APPLICATION FOR IMPLEADMENT"},{"diary_no":323162019,"reg_no_display":"SLP(Crl) No. 8174\/2019","pet_name":"M\/S ADVANTAGE INDIA","res_name":"UNION OF INDIA","pno":5,"rno":5,"next_date":"","doc_number":"137540\/2019","doc_filing_date":"2019-09-06 12:57:31","doc_title":"EXEMPTION FROM FILING C\/C OF THE IMPUGNED JUDGMENT-"},{"diary_no":280552019,"reg_no_display":"W.P.(C) No. 1013\/2019","pet_name":"MANOHAR LAL SHARMA","res_name":"UNION OF INDIA","pno":1,"rno":2,"next_date":"","doc_number":"136293\/2019","doc_filing_date":"2019-09-04 16:07:59","doc_title":"INTERVENTION\/IMPLEADMENT-IA FOR IMPLEADMENT"},{"diary_no":297962019,"reg_no_display":"W.P.(C) No. 1099\/2019","pet_name":"SHAH FAESAL","res_name":"UNION OF INDIA","pno":8,"rno":2,"next_date":"","doc_number":"136349\/2019","doc_filing_date":"2019-09-04 16:26:12","doc_title":"INTERVENTION\/IMPLEADMENT-AN APPLICATION FOR IMPLEADMENT"},{"diary_no":285632019,"reg_no_display":"W.P.(C) No. 1048\/2019","pet_name":"SHAKIR SHABIR","res_name":"UNION OF INDIA","pno":1,"rno":3,"next_date":"","doc_number":"136357\/2019","doc_filing_date":"2019-09-04 16:29:16","doc_title":"INTERVENTION\/IMPLEADMENT-AN APPLICATION FOR IMPLEADMENT"},{"diary_no":296062019,"reg_no_display":"W.P.(C) No. 1070\/2019","pet_name":"RADHA KUMAR","res_name":"UNION OF INDIA","pno":6,"rno":2,"next_date":"","doc_number":"136314\/2019","doc_filing_date":"2019-09-04 16:15:31","doc_title":"INTERVENTION\/IMPLEADMENT-AN APPLICATION FOR IMPLEADMENT"},{"diary_no":240332019,"reg_no_display":"SLP(C) No. 16845\/2019","pet_name":"APOORVA DABAS","res_name":"GOVT. OF NCT OF DELHI","pno":8,"rno":10,"next_date":"","doc_number":"137874\/2019","doc_filing_date":"2019-09-06 15:02:05","doc_title":"APPLICATION FOR TRANSPOSITION-"},{"diary_no":286812019,"reg_no_display":"W.P.(C) No. 1068\/2019","pet_name":"SOAYIB QURESHI","res_name":"UNION OF INDIA","pno":1,"rno":3,"next_date":"","doc_number":"136304\/2019","doc_filing_date":"2019-09-04 16:11:46","doc_title":"INTERVENTION\/IMPLEADMENT-I A FOR IMPLEADEMENT"},{"diary_no":290012019,"reg_no_display":"W.P.(C) No. 1062\/2019","pet_name":"INDER SALIM ALIAS INDER JI TICKOO","res_name":"UNION OF INDIA","pno":2,"rno":3,"next_date":"","doc_number":"136347\/2019","doc_filing_date":"2019-09-04 16:25:26","doc_title":"INTERVENTION\/IMPLEADMENT-IA FOR IMPLEADMENT"},{"diary_no":309452019,"reg_no_display":"W.P.(C) No. 1104\/2019","pet_name":"MUZZAFAR IQBAL KHAN","res_name":"UNION OF INDIA","pno":1,"rno":3,"next_date":"","doc_number":"136313\/2019","doc_filing_date":"2019-09-04 16:14:07","doc_title":"INTERVENTION\/IMPLEADMENT-IA FOR IMPLEADMENT"},{"diary_no":288032019,"reg_no_display":"W.P.(C) No. 1037\/2019","pet_name":"MOHD. AKBAR LONE","res_name":"UNION OF INDIA","pno":2,"rno":3,"next_date":"","doc_number":"136356\/2019","doc_filing_date":"2019-09-04 16:29:01","doc_title":"INTERVENTION\/IMPLEADMENT-IA FOR IMPLEADMENT"},{"diary_no":285202019,"reg_no_display":"W.P.(C) No. 1082\/2019","pet_name":"FAROOQ AHMAD DAR","res_name":"UNION OF INDIA","pno":1,"rno":4,"next_date":"","doc_number":"136299\/2019","doc_filing_date":"2019-09-04 16:10:37","doc_title":"INTERVENTION\/IMPLEADMENT-IA FOR IMPLEADMENT"},{"diary_no":320632019,"reg_no_display":"SLP(C) No. 21477\/2019","pet_name":"PARAMJIT SINGH NAGI","res_name":"UNION OF INDIA","pno":1,"rno":4,"next_date":"2020-04-09","doc_number":"136359\/2019","doc_filing_date":"2019-09-04 16:29:40","doc_title":"EXEMPTION FROM FILING C\/C OF THE IMPUGNED JUDGMENT-"},{"diary_no":208722019,"reg_no_display":"W.P.(C) No. 819\/2019","pet_name":"BHAVIKA","res_name":"UNION OF INDIA","pno":1,"rno":36,"next_date":"","doc_number":"137755\/2019","doc_filing_date":"2019-09-06 14:37:18","doc_title":"INTERVENTION APPLICATION-"},{"diary_no":313022019,"reg_no_display":"SLP(Crl) No. 9685\/2019","pet_name":"YOGESH YADAV","res_name":"ANIL BHATI","pno":1,"rno":3,"next_date":"","doc_number":"135374\/2019","doc_filing_date":"2019-09-03 15:53:19","doc_title":"EXEMPTION FROM FILING O.T.-"},{"diary_no":313022019,"reg_no_display":"SLP(Crl) No. 9685\/2019","pet_name":"YOGESH YADAV","res_name":"ANIL BHATI","pno":1,"rno":3,"next_date":"","doc_number":"135375\/2019","doc_filing_date":"2019-09-03 15:53:49","doc_title":"PERMISSION TO FILE PETITION (SLP\/TP\/WP\/..)-"},{"diary_no":221492019,"reg_no_display":"Crl.A. No. 1337\/2019","pet_name":"NARESH KUMAR","res_name":"STATE OF NCT OF DELHI","pno":1,"rno":2,"next_date":"","doc_number":"135259\/2019","doc_filing_date":"2019-09-03 15:12:07","doc_title":"GRANT OF BAIL-APPLICATION FOR EGULAR BAIL ON BEHALF OF THE APPELLANT"}]},"warnings":[],"errors":[]}